sfqlib/__init__.py
sfqlib/_sfqQubitLegacy.py
sfqlib/bloch.py
sfqlib/euler_angle.py
sfqlib/sfqQubit.py
sfqlib/sweep.py
sfqlib-0.1.4.dist-info/DESCRIPTION.rst
sfqlib-0.1.4.dist-info/METADATA
sfqlib-0.1.4.dist-info/RECORD
sfqlib-0.1.4.dist-info/WHEEL
sfqlib-0.1.4.dist-info/metadata.json
sfqlib-0.1.4.dist-info/top_level.txt
