Metadata-Version: 2.0
Name: sfqlib
Version: 0.1.4
Summary: Tools for SFQ research
Home-page: https://github.com/hannoeichel/sfqlib
Author: Kangbo Li
Author-email: kli89@wisc.edu
License: MIT
Keywords: SFQ,Control
Platform: UNKNOWN
Requires-Dist: numpy
Requires-Dist: scipy
